moctopus/__init__.py
moctopus-0.1.0.dist-info/METADATA
moctopus-0.1.0.dist-info/WHEEL
moctopus-0.1.0.dist-info/top_level.txt
moctopus-0.1.0.dist-info/RECORD
